{
    "address": "PO BOX 287",
    "city": "BETHEL",
    "county_name": "BETHEL",
    "emergency_services": true,
    "global_rank": {},
    "hospital_name": "YUKON KUSKOKWIM DELTA REG HOSPITAL",
    "hospital_ownership": "Government - Federal",
    "hospital_type": "Acute Care Hospitals",
    "location": {
        "human_address": "{\"address\":\"PO BOX 287\",\"city\":\"BETHEL\",\"state\":\"AK\",\"zip\":\"\"}",
        "latitude": "60.79428899100003",
        "longitude": "-161.76086713599997",
        "needs_recoding": false
    },
    "location_address": "PO BOX 287",
    "location_city": "BETHEL",
    "location_state": "AK",
    "location_zip": "99559",
    "network_info": {
        "arin_handles": [],
        "as_numbers": [],
        "netblock_ranges": [],
        "websites": [
            "www.alaskaregional.com"
        ]
    },
    "numeric_ratings": {},
    "parent_info": {
        "name": null,
        "websites": []
    },
    "phone_number": "9075436300",
    "provider_id": "020018",
    "raw_ratings": {},
    "state": "AK",
    "zip_code": "99559"
}