{
    "address": "2801 MEDICAL CENTER DRIVE", 
    "city": "POCAHONTAS", 
    "county_name": "RANDOLPH", 
    "effectiveness_of_care_national_comparison": "Same as the National average", 
    "efficient_use_of_medical_imaging_national_comparison": "Not Available", 
    "efficient_use_of_medical_imaging_national_comparison_footnote": "Results are not available for this reporting period", 
    "emergency_services": true, 
    "global_rank": {}, 
    "hospital_name": "FIVE RIVERS MEDICAL CENTER", 
    "hospital_overall_rating": "3", 
    "hospital_ownership": "Voluntary non-profit - Private", 
    "hospital_type": "Acute Care Hospitals", 
    "location": {
        "coordinates": [
            -90.996399, 
            36.289907
        ], 
        "type": "Point"
    }, 
    "location_address": "2801 MEDICAL CENTER DRIVE", 
    "location_city": "POCAHONTAS", 
    "location_state": "AR", 
    "location_zip": "72455", 
    "mortality_national_comparison": "Same as the National average", 
    "network_info": {
        "arin_handles": [], 
        "as_numbers": [], 
        "netblock_ranges": [], 
        "websites": []
    }, 
    "numeric_ratings": {}, 
    "parent_info": {
        "name": null, 
        "websites": []
    }, 
    "patient_experience_national_comparison": "Not Available", 
    "patient_experience_national_comparison_footnote": "Results are not available for this reporting period", 
    "phone_number": "8708926000", 
    "provider_id": "040047", 
    "raw_ratings": {}, 
    "readmission_national_comparison": "Same as the National average", 
    "safety_of_care_national_comparison": "Not Available", 
    "safety_of_care_national_comparison_footnote": "Results are not available for this reporting period", 
    "state": "AR", 
    "timeliness_of_care_national_comparison": "Above the National average", 
    "zip_code": "72455"
}