{
    "address": "2325 CORONADO STREET",
    "city": "IDAHO FALLS",
    "county_name": "BONNEVILLE",
    "emergency_services": true,
    "global_rank": {},
    "hospital_name": "MOUNTAIN VIEW HOSPITAL",
    "hospital_ownership": "Proprietary",
    "hospital_type": "Acute Care Hospitals",
    "location": {
        "coordinates": [
            -111.987748,
            43.472521
        ],
        "type": "Point"
    },
    "location_address": "2325 CORONADO STREET",
    "location_city": "IDAHO FALLS",
    "location_state": "ID",
    "location_zip": "83404",
    "network_info": {
        "arin_handles": [],
        "as_numbers": [],
        "netblock_ranges": [],
        "websites": [
            "www.mountainviewhospital.org"
        ]
    },
    "numeric_ratings": {},
    "parent_info": {
        "name": null,
        "websites": []
    },
    "phone_number": "2085572711",
    "provider_id": "130065",
    "raw_ratings": {},
    "state": "ID",
    "zip_code": "83404"
}