{
    "address": "4455 EDISON LAKES PKWY", 
    "city": "MISHAWAKA", 
    "county_name": "ST JOSEPH", 
    "effectiveness_of_care_national_comparison": "Same as the National average", 
    "efficient_use_of_medical_imaging_national_comparison": "Not Available", 
    "efficient_use_of_medical_imaging_national_comparison_footnote": "Results are not available for this reporting period", 
    "emergency_services": false, 
    "global_rank": {}, 
    "hospital_name": "UNITY MEDICAL AND SURGICAL HOSPITAL", 
    "hospital_overall_rating_footnote": "There are too few measures or measure groups reported to calculate a star rating or measure group score", 
    "hospital_ownership": "Proprietary", 
    "hospital_type": "Acute Care Hospitals", 
    "location": {
        "coordinates": [
            -86.177998, 
            41.702328
        ], 
        "type": "Point"
    }, 
    "location_address": "4455 EDISON LAKES PKWY", 
    "location_city": "MISHAWAKA", 
    "location_state": "IN", 
    "location_zip": "46545", 
    "mortality_national_comparison": "Not Available", 
    "mortality_national_comparison_footnote": "Results are not available for this reporting period", 
    "network_info": {
        "arin_handles": [], 
        "as_numbers": [], 
        "netblock_ranges": [], 
        "websites": [
            "www.monroehospital.com"
        ]
    }, 
    "numeric_ratings": {}, 
    "parent_info": {
        "name": null, 
        "websites": []
    }, 
    "patient_experience_national_comparison": "Above the National average", 
    "phone_number": "5742316800", 
    "provider_id": "150177", 
    "raw_ratings": {}, 
    "readmission_national_comparison": "Not Available", 
    "readmission_national_comparison_footnote": "Results are not available for this reporting period", 
    "safety_of_care_national_comparison": "Not Available", 
    "safety_of_care_national_comparison_footnote": "Results are not available for this reporting period", 
    "state": "IN", 
    "timeliness_of_care_national_comparison": "Not Available", 
    "timeliness_of_care_national_comparison_footnote": "Results are not available for this reporting period", 
    "zip_code": "46545"
}