{
    "address": "7900 LEE'S SUMMIT RD", 
    "city": "KANSAS CITY", 
    "county_name": "JACKSON", 
    "effectiveness_of_care_national_comparison": "Same as the National average", 
    "efficient_use_of_medical_imaging_national_comparison": "Not Available", 
    "efficient_use_of_medical_imaging_national_comparison_footnote": "Results are not available for this reporting period", 
    "emergency_services": true, 
    "global_rank": {}, 
    "hospital_name": "TRUMAN MEDICAL CENTER LAKEWOOD", 
    "hospital_overall_rating": "2", 
    "hospital_ownership": "Voluntary non-profit - Private", 
    "hospital_type": "Acute Care Hospitals", 
    "location": {
        "coordinates": [
            -94.39046, 
            38.973566
        ], 
        "type": "Point"
    }, 
    "location_address": "7900 LEE'S SUMMIT RD", 
    "location_city": "KANSAS CITY", 
    "location_state": "MO", 
    "location_zip": "64139", 
    "mortality_national_comparison": "Not Available", 
    "mortality_national_comparison_footnote": "Results are not available for this reporting period", 
    "network_info": {
        "arin_handles": [], 
        "as_numbers": [], 
        "netblock_ranges": [], 
        "websites": [
            "www.trumed.org"
        ]
    }, 
    "numeric_ratings": {}, 
    "parent_info": {
        "name": "Truman Medical Centers", 
        "websites": [
            "www.trumed.org"
        ]
    }, 
    "patient_experience_national_comparison": "Below the National average", 
    "phone_number": "8164047000", 
    "provider_id": "260102", 
    "raw_ratings": {}, 
    "readmission_national_comparison": "Same as the National average", 
    "safety_of_care_national_comparison": "Same as the National average", 
    "state": "MO", 
    "timeliness_of_care_national_comparison": "Same as the National average", 
    "zip_code": "64139"
}