{
    "address": "100 N E SAINT LUKE'S BOULEVARD",
    "city": "LEES SUMMIT",
    "county_name": "JACKSON",
    "emergency_services": true,
    "global_rank": {},
    "hospital_name": "SAINT LUKE'S EAST LEE'S SUMMIT HOSPITAL",
    "hospital_ownership": "Voluntary non-profit - Private",
    "hospital_type": "Acute Care Hospitals",
    "location": {
        "human_address": "{\"address\":\"100 N E SAINT LUKE'S BOULEVARD\",\"city\":\"LEES SUMMIT\",\"state\":\"MO\",\"zip\":\"\"}",
        "latitude": "38.94154663200004",
        "longitude": "-94.38159919199995",
        "needs_recoding": false
    },
    "network_info": {
        "arin_handles": [],
        "as_numbers": [],
        "netblock_ranges": [],
        "websites": [
            "www.saintlukeshealthsystem.org"
        ]
    },
    "numeric_ratings": {},
    "parent_info": {
        "name": "Saint Luke's Health System",
        "websites": [
            "www.saintlukeshealthsystem.org"
        ]
    },
    "phone_number": {
        "phone_number": "8163475000"
    },
    "provider_id": "260216",
    "raw_ratings": {},
    "state": "MO",
    "zip_code": "64086"
}