{
    "address": "555 ST JOSEPH'S BLVD",
    "city": "ELMIRA",
    "county_name": "CHEMUNG",
    "emergency_services": true,
    "global_rank": {},
    "hospital_name": "ST JOSEPH'S HOSPITAL, INC",
    "hospital_ownership": "Voluntary non-profit - Private",
    "hospital_type": "Acute Care Hospitals",
    "location": {
        "coordinates": [
            -76.796843,
            42.091393
        ],
        "type": "Point"
    },
    "location_address": "555 ST JOSEPH'S BLVD",
    "location_city": "ELMIRA",
    "location_state": "NY",
    "location_zip": "14902",
    "network_info": {
        "arin_handles": [],
        "as_numbers": [],
        "netblock_ranges": [],
        "websites": [
            "www.stjosephs.org"
        ]
    },
    "numeric_ratings": {},
    "parent_info": {
        "name": null,
        "websites": []
    },
    "phone_number": "6077336541",
    "provider_id": "330108",
    "raw_ratings": {},
    "state": "NY",
    "zip_code": "14902"
}