{
    "address": "1341 NORTH CLARK STREET",
    "city": "CAMBRIDGE",
    "county_name": "GUERNSEY",
    "emergency_services": true,
    "global_rank": {},
    "hospital_name": "SOUTHEASTERN OHIO REGIONAL MEDICAL CENTER",
    "hospital_ownership": "Voluntary non-profit - Private",
    "hospital_type": "Acute Care Hospitals",
    "location": {
        "human_address": "{\"address\":\"1341 NORTH CLARK STREET\",\"city\":\"CAMBRIDGE\",\"state\":\"OH\",\"zip\":\"\"}",
        "latitude": "40.04014567400003",
        "longitude": "-81.57678957799999",
        "needs_recoding": false
    },
    "network_info": {
        "arin_handles": [],
        "as_numbers": [],
        "netblock_ranges": [],
        "websites": [
            "www.seormc.org"
        ]
    },
    "numeric_ratings": {},
    "parent_info": {
        "name": null,
        "websites": []
    },
    "phone_number": {
        "phone_number": "7404398111"
    },
    "provider_id": "360203",
    "raw_ratings": {},
    "state": "OH",
    "zip_code": "43725"
}