{
    "address": "2220 IOWA STREET",
    "city": "CHICKASHA",
    "county_name": "GRADY",
    "emergency_services": true,
    "global_rank": {},
    "hospital_name": "GRADY MEMORIAL HOSPITAL",
    "hospital_ownership": "Government - Hospital District or Authority",
    "hospital_type": "Acute Care Hospitals",
    "location": {
        "human_address": "{\"address\":\"2220 IOWA STREET\",\"city\":\"CHICKASHA\",\"state\":\"OK\",\"zip\":\"\"}",
        "latitude": "35.04697502400006",
        "longitude": "-97.92880321799998",
        "needs_recoding": false
    },
    "network_info": {
        "arin_handles": [],
        "as_numbers": [],
        "netblock_ranges": [],
        "websites": [
            "www.gradymem.org"
        ]
    },
    "numeric_ratings": {},
    "parent_info": {
        "name": null,
        "websites": []
    },
    "phone_number": {
        "phone_number": "4052242300"
    },
    "provider_id": "370054",
    "raw_ratings": {},
    "state": "OK",
    "zip_code": "73018"
}