{
    "address": "100 FAIRFIELD DRIVE",
    "city": "SENECA",
    "county_name": "VENANGO",
    "emergency_services": true,
    "global_rank": {},
    "hospital_name": "UPMC NORTHWEST",
    "hospital_ownership": "Voluntary non-profit - Other",
    "hospital_type": "Acute Care Hospitals",
    "location": {
        "human_address": "{\"address\":\"100 FAIRFIELD DRIVE\",\"city\":\"SENECA\",\"state\":\"PA\",\"zip\":\"\"}",
        "latitude": "41.35999054700005",
        "longitude": "-79.70782225999994",
        "needs_recoding": false
    },
    "network_info": {
        "arin_handles": [],
        "as_numbers": [],
        "netblock_ranges": [],
        "websites": [
            "northwest.upmc.com"
        ]
    },
    "numeric_ratings": {},
    "parent_info": {
        "name": "University of Pittsburgh Medical Center",
        "websites": [
            "www.upmc.com"
        ]
    },
    "phone_number": {
        "phone_number": "8146767600"
    },
    "provider_id": "390091",
    "raw_ratings": {},
    "state": "PA",
    "zip_code": "16346"
}