{
    "address": "1115 LANE 12", 
    "city": "LOVELL", 
    "county_name": "BIG HORN", 
    "effectiveness_of_care_national_comparison": "Not Available", 
    "effectiveness_of_care_national_comparison_footnote": "Results are not available for this reporting period", 
    "efficient_use_of_medical_imaging_national_comparison": "Not Available", 
    "efficient_use_of_medical_imaging_national_comparison_footnote": "Results are not available for this reporting period", 
    "emergency_services": true, 
    "global_rank": {}, 
    "hospital_name": "NORTH BIG HORN HOSPITAL DISTRICT", 
    "hospital_overall_rating_footnote": "There are too few measures or measure groups reported to calculate a star rating or measure group score", 
    "hospital_ownership": "Government - Hospital District or Authority", 
    "hospital_type": "Critical Access Hospitals", 
    "location": {
        "coordinates": [
            -108.390126, 
            44.825802
        ], 
        "type": "Point"
    }, 
    "location_address": "1115 LANE 12", 
    "location_city": "LOVELL", 
    "location_state": "WY", 
    "location_zip": "82431", 
    "mortality_national_comparison": "Not Available", 
    "mortality_national_comparison_footnote": "Results are not available for this reporting period", 
    "network_info": {
        "arin_handles": [], 
        "as_numbers": [], 
        "netblock_ranges": [], 
        "websites": [
            "www.nbhh.com"
        ]
    }, 
    "numeric_ratings": {}, 
    "parent_info": {
        "name": null, 
        "websites": []
    }, 
    "patient_experience_national_comparison": "Not Available", 
    "patient_experience_national_comparison_footnote": "Results are not available for this reporting period", 
    "phone_number": "3075485200", 
    "provider_id": "531309", 
    "raw_ratings": {}, 
    "readmission_national_comparison": "Not Available", 
    "readmission_national_comparison_footnote": "Results are not available for this reporting period", 
    "safety_of_care_national_comparison": "Not Available", 
    "safety_of_care_national_comparison_footnote": "Results are not available for this reporting period", 
    "state": "WY", 
    "timeliness_of_care_national_comparison": "Not Available", 
    "timeliness_of_care_national_comparison_footnote": "Results are not available for this reporting period", 
    "zip_code": "82431"
}